iscontain/__init__.py
iscontain/iscontain.py
iscontain-0.1.dist-info/LICENSE
iscontain-0.1.dist-info/METADATA
iscontain-0.1.dist-info/WHEEL
iscontain-0.1.dist-info/top_level.txt
iscontain-0.1.dist-info/RECORD
