Metadata-Version: 2.1
Name: iscontain
Version: 0.1
Summary: It can check if A is a subset of B based on python 3.10
Home-page: https://github.com/SHYChePi/iscontain/
Author: SHYChePi
License: UNKNOWN
Platform: UNKNOWN
Classifier: Programming Language :: Python :: 3
Classifier: License :: OSI Approved :: MIT License
Classifier: Operating System :: OS Independent
License-File: LICENSE
